{"data":[{"start":"8:15 PM","end":"9:12 PM","activity":"Workout","class":null,"belt":"1761645","meps":"126","duration":"57","timeInZone":"39","avgEffort":"65%","avgHR":"126","calories":"599","peakHR":"160","GUID":"19df3f72-f78d-11e9-a43e-ac1f6b49537a","rank":1,"rankText":"Iron","isoDate":"2019-10-25","timestamp":1572034530,"date":"Fri 25 Oct 2019","altdate":"Fri 25 Oct 2019","sStart":"2019-10-25 20:15:30","sEnd":"2019-10-25 21:12:22","avgEffortValue":65,"range":"8:15 PM to 9:12 PM","zoneMins":[9,8,10,22,8,0],"zoneMEPs":[0,8,20,66,32,0],"isClass":false,"url":"myzone.org"}],"totals": "Totals","kcal": "KCal","createdBy": "Created By","gym": "MZUS001","owner":{"firstName":"Matt","surname":"Miorelli","nickname":"Zan"}}