{"data":[{"start":"2:03 PM","end":"3:13 PM","activity":"Workout","class":null,"belt":"1761645","meps":"179","duration":"69","timeInZone":"49","avgEffort":"70%","avgHR":"134","calories":"805","peakHR":"167","GUID":"ff1e7c86-f822-11e9-a43e-ac1f6b49537a","rank":1,"rankText":"Iron","isoDate":"2019-10-26","timestamp":1572098631,"date":"Sat 26 Oct 2019","altdate":"Sat 26 Oct 2019","sStart":"2019-10-26 14:03:51","sEnd":"2019-10-26 15:13:00","avgEffortValue":70,"range":"2:03 PM to 3:13 PM","zoneMins":[12,8,5,15,29,0],"zoneMEPs":[0,8,10,45,116,0],"isClass":false,"url":"myzone.org"}],"totals": "Totals","kcal": "KCal","createdBy": "Created By","gym": "MZUS001","owner":{"firstName":"Matt","surname":"Miorelli","nickname":"Zan"}}