{"data":[{"start":"6:58 PM","end":"9:21 PM","activity":"Just break your fucking leg already Joe","class":null,"belt":"1766013","meps":"266","duration":"143","timeInZone":"85","avgEffort":"62%","avgHR":"119","calories":"1334","peakHR":"165","GUID":"1787671b-fc34-11e9-92e3-ac1f6b49537a","rank":1,"rankText":"Iron","isoDate":"2019-10-31","timestamp":1572548280,"date":"Thu 31 Oct 2019","altdate":"Thu 31 Oct 2019","sStart":"2019-10-31 18:58:00","sEnd":"2019-10-31 21:21:44","avgEffortValue":62,"range":"6:58 PM to 9:21 PM","zoneMins":[35,23,33,31,21,0],"zoneMEPs":[0,23,66,93,84,0],"isClass":false,"url":"myzone.org"}],"totals": "Totals","kcal": "KCal","createdBy": "Created By","gym": "MZUS001","owner":{"firstName":"Daniel","surname":"Grodziak","nickname":"Denim"}}