{"data":[{"start":"6:46 AM","end":"7:33 AM","activity":"Cardio is for cunts","class":null,"belt":"1766013","meps":"65","duration":"47","timeInZone":"19","avgEffort":"58%","avgHR":"112","calories":"333","peakHR":"161","GUID":"61f780e2-fefb-11e9-92e3-ac1f6b49537a","rank":1,"rankText":"Iron","isoDate":"2019-11-04","timestamp":1572849990,"date":"Mon 04 Nov 2019","altdate":"Mon 04 Nov 2019","sStart":"2019-11-04 06:46:30","sEnd":"2019-11-04 07:33:00","avgEffortValue":58,"range":"6:46 AM to 7:33 AM","zoneMins":[18,10,5,11,3,0],"zoneMEPs":[0,10,10,33,12,0],"isClass":false,"url":"myzone.org"}],"totals": "Totals","kcal": "KCal","createdBy": "Created By","gym": "MZUS001","owner":{"firstName":"Daniel","surname":"Grodziak","nickname":"Denim"}}